IlyasMessageProtocol/__init__.py
IlyasMessageProtocol/protocol.py
ilyasmessageprotocol-0.1.1.dist-info/METADATA
ilyasmessageprotocol-0.1.1.dist-info/WHEEL
ilyasmessageprotocol-0.1.1.dist-info/top_level.txt
ilyasmessageprotocol-0.1.1.dist-info/RECORD
