Metadata-Version: 2.4
Name: IlyasMessageProtocol
Version: 0.1.1
Summary: Моя библиотека imp_utils
Author-email: Qwamatata <malyutin.2011@list.ru>
Requires-Python: >=3.8
